rdkit_mcp/__init__.py
rdkit_mcp/base_tools.py
rdkit_mcp/decorators.py
rdkit_mcp/register_tools.py
rdkit_mcp/settings.py
rdkit_mcp/types.py
rdkit_mcp/utils.py
rdkit_mcp/Chem/Descriptors.py
rdkit_mcp/Chem/Draw.py
rdkit_mcp/Chem/__init__.py
rdkit_mcp/Chem/rdMMPA.py
rdkit_mcp/Chem/rdMolDescriptors.py
rdkit_mcp/Chem/Scaffolds/MurckoScaffold.py
rdkit_mcp/Chem/Scaffolds/__init__.py
rdkit_mcp/Chem/rdchem/Mol.py
rdkit_mcp/Chem/rdchem/__init__.py
rdkit_mcp/DataStructs/TanimotoSimilarity.py
rdkit_mcp/DataStructs/__init__.py
rdkit_mcp_clients/openai.py
mseep_rdkit_mcp_server-0.1.6.dist-info/METADATA
mseep_rdkit_mcp_server-0.1.6.dist-info/WHEEL
mseep_rdkit_mcp_server-0.1.6.dist-info/entry_points.txt
mseep_rdkit_mcp_server-0.1.6.dist-info/licenses/LICENSE
mseep_rdkit_mcp_server-0.1.6.dist-info/RECORD
