Metadata-Version: 2.4
Name: mseep-rdkit-mcp-server
Version: 0.1.6
Summary: MCP Server providing RDKit cheminformatics tools.
Project-URL: Homepage, https://github.com/tandem-ai-inc/rdkit-mcp-server
Project-URL: Repository, https://github.com/tandem-ai-inc/rdkit-mcp-server
Author-email: mseep <support@skydeck.ai>
License: MIT License
License-File: LICENSE
Classifier: Framework :: AsyncIO
Classifier: Operating System :: OS Independent
Classifier: Programming Language :: Python :: 3
Classifier: Topic :: Scientific/Engineering :: Chemistry
Requires-Python: >=3.8
Requires-Dist: mcp==1.11.0
Requires-Dist: openai-agents==0.0.14
Requires-Dist: pillow==11.2.1
Requires-Dist: pydantic-settings==2.9.1
Requires-Dist: pydantic==2.11.5
Requires-Dist: pyyaml
Requires-Dist: rdkit==2025.3.1
